server_discovery/__init__.py
server_discovery/_broadcast.py
server_discovery/_client.py
server_discovery/_info_model.py
server_discovery/_server.py
server_discovery-0.1.1.dist-info/METADATA
server_discovery-0.1.1.dist-info/WHEEL
server_discovery-0.1.1.dist-info/top_level.txt
server_discovery-0.1.1.dist-info/RECORD
