Metadata-Version: 2.1
Name: server-discovery
Version: 0.1.1
Summary: Automatically find your server(s) by port on the local network
Project-URL: Homepage, https://github.com/SamuLumio/server-discovery
Requires-Dist: pydantic
Requires-Dist: netifaces
